dot_tree/__init__.py
dot_tree/classes/__init__.py
dot_tree/classes/assets.py
dot_tree/classes/pygame.py
python_dot_tree-1.0.8.dist-info/LICENSE
python_dot_tree-1.0.8.dist-info/METADATA
python_dot_tree-1.0.8.dist-info/WHEEL
python_dot_tree-1.0.8.dist-info/top_level.txt
python_dot_tree-1.0.8.dist-info/RECORD
